demo/__init__.py
demo/hello.py
goodstar-0.0.1.dist-info/METADATA
goodstar-0.0.1.dist-info/WHEEL
goodstar-0.0.1.dist-info/top_level.txt
goodstar-0.0.1.dist-info/RECORD
